{
    "type": "UIListView",
    "config": {
        "listClassName": "",
        "className": "",
        "viewType": "view",
        "namedView": "singleArchivedProjectListItemDetail",
        "shouldRender": true,
        "namedViewScript": "return namedView",
        "showInlineEdit": false,
        "namedFormView": "defaultFormView",
        "formOptions": "{}",
        "showDeleteButton": false,
        "deleteItemScript": "",
        "formatModuleScript": "",
        "resolveItemScript": "return item",
        "filterModulesScript": "return list",
        "itemButtonsScript": "return [];",
        "insertAtTop": false,
        "getItemListScript": "ProjectTeam.CurrentTeam().getArchivedProjects(callback);",
        "formatItemListScript": "return list;",
        "formatListItemModuleScript": "",
        "emptyNamedView": "emptyListView",
        "filterItemsScript": "return true;",
        "sortItemsScript": "",
        "maxItems": "-1"
    }
}